am4894ga/__init__.py
am4894ga/_nbdev.py
am4894ga/core.py
am4894ga-0.0.6.dist-info/LICENSE
am4894ga-0.0.6.dist-info/METADATA
am4894ga-0.0.6.dist-info/WHEEL
am4894ga-0.0.6.dist-info/entry_points.txt
am4894ga-0.0.6.dist-info/top_level.txt
am4894ga-0.0.6.dist-info/RECORD
